odoo/addons/shopinvader_locomotive_algolia/README.rst
odoo/addons/shopinvader_locomotive_algolia/__init__.py
odoo/addons/shopinvader_locomotive_algolia/__manifest__.py
odoo/addons/shopinvader_locomotive_algolia/component/__init__.py
odoo/addons/shopinvader_locomotive_algolia/component/shopinvader_site_export_mapper.py
odoo/addons/shopinvader_locomotive_algolia/i18n/shopinvader_locomotive_algolia.pot
odoo/addons/shopinvader_locomotive_algolia/readme/CONTRIBUTORS.rst
odoo/addons/shopinvader_locomotive_algolia/readme/CREDITS.rst
odoo/addons/shopinvader_locomotive_algolia/readme/DESCRIPTION.rst
odoo/addons/shopinvader_locomotive_algolia/readme/HISTORY.rst
odoo/addons/shopinvader_locomotive_algolia/static/description/index.html
odoo/addons/shopinvader_locomotive_algolia/tests/__init__.py
odoo/addons/shopinvader_locomotive_algolia/tests/test_search_engine_site_export.py
odoo12_addon_shopinvader_locomotive_algolia-12.0.1.0.0.99.dev3.dist-info/METADATA
odoo12_addon_shopinvader_locomotive_algolia-12.0.1.0.0.99.dev3.dist-info/WHEEL
odoo12_addon_shopinvader_locomotive_algolia-12.0.1.0.0.99.dev3.dist-info/top_level.txt
odoo12_addon_shopinvader_locomotive_algolia-12.0.1.0.0.99.dev3.dist-info/RECORD
