Metadata-Version: 2.1
Name: odoo12-addon-shopinvader_locomotive_algolia
Version: 12.0.1.0.0.99.dev3
Summary: This addons is used to push the initial algolia configuration to locomotive
Home-page: https://github.com/shopinvader/odoo-shopinvader
Author: Camptcamp SA
License: AGPL-3
Classifier: Programming Language :: Python
Classifier: Framework :: Odoo
Classifier: Framework :: Odoo :: 12.0
Classifier: License :: OSI Approved :: GNU Affero General Public License v3
Requires-Python: >=3.5
Requires-Dist: odoo12-addon-component
Requires-Dist: odoo12-addon-shopinvader-algolia
Requires-Dist: odoo12-addon-shopinvader-locomotive
Requires-Dist: odoo<12.1dev,>=12.0a
